gamma/io/__init__.py
gamma/io/__version__.py
gamma/io/_arrow.py
gamma/io/_dataset.py
gamma/io/_fs.py
gamma/io/_logging.py
gamma/io/_pandas.py
gamma/io/_polars.py
gamma/io/_sql.py
gamma/io/_staging.py
gamma/io/_types.py
gamma/io/_utils.py
gamma/io/config.py
gamma_io-0.1.9.dist-info/METADATA
gamma_io-0.1.9.dist-info/WHEEL
gamma_io-0.1.9.dist-info/RECORD
