Metadata-Version: 2.1
Name: gamma-io
Version: 0.1.9
Summary: Extensible library for interacting with datasets in data intensive projects
Author-Email: Cloves Almeida <almeida.cloves@bcg.com>
License: MIT
Requires-Python: >=3.10
Requires-Dist: click>=7
Requires-Dist: tqdm
Requires-Dist: pandas>=2
Requires-Dist: pyarrow>=12
Requires-Dist: pydantic>=2
Requires-Dist: fsspec>=2023
Requires-Dist: decorator>=4
Requires-Dist: polars>=0.18; extra == "polars"
Requires-Dist: polars>=0.18; extra == "full"
Requires-Dist: gamma-config>=0.7; extra == "full"
Requires-Dist: s3fs>=2023; extra == "full"
Requires-Dist: sqlalchemy>=2; extra == "full"
Requires-Dist: jinja2>=2; extra == "full"
Requires-Dist: s3fs>=2023; extra == "aws"
Requires-Dist: sqlalchemy>=2; extra == "sql"
Provides-Extra: polars
Provides-Extra: full
Provides-Extra: aws
Provides-Extra: sql
